blochpesto/DFT.py
blochpesto/XPS.py
blochpesto/__init__.py
blochpesto/base.py
blochpesto/bloch.py
blochpesto/export.py
blochpesto/interactive.py
blochpesto/spin.py
blochpesto/assets/bcc(100).png
blochpesto/assets/bcc(110).png
blochpesto/assets/bcc_100.png
blochpesto/assets/fcc(100).png
blochpesto/assets/fcc(110).png
blochpesto/assets/fcc(111).png
blochpesto/assets/gr2400_2.25_resolution.txt
blochpesto/assets/gr800_2.25_resolution.txt
blochpesto/assets/gr92_2.25_resolution.txt
blochpesto/assets/hcp(0001).png
blochpesto/fileLoaders/Bloch_pickle.py
blochpesto/fileLoaders/Prodigy_itx.py
blochpesto/fileLoaders/Prodigy_sp2.py
blochpesto/fileLoaders/Prodigy_xy.py
blochpesto/fileLoaders/SES_ibw.py
blochpesto/fileLoaders/SES_txt.py
blochpesto/fileLoaders/SES_zip.py
blochpesto/fileLoaders/__init__.py
blochpesto/fileLoaders/i4_sr.py
blochpesto/fileLoaders/nxs.py
blochpesto-1.1.1.dist-info/METADATA
blochpesto-1.1.1.dist-info/WHEEL
blochpesto-1.1.1.dist-info/licenses/LICENSE
blochpesto-1.1.1.dist-info/RECORD
