Metadata-Version: 2.4
Name: blochpesto
Version: 1.1.1
Summary: Analysis and visualization package for ARPES data
Project-URL: Homepage, https://pesto.readthedocs.io
Author-email: Craig Polley <craig.polley@maxiv.lu.se>
License-Expression: MIT
License-File: LICENSE
Classifier: Operating System :: OS Independent
Classifier: Programming Language :: Python :: 3
Requires-Python: >=3.8
Requires-Dist: astropy
Requires-Dist: h5py
Requires-Dist: igor2
Requires-Dist: ipympl>=0.9.3
Requires-Dist: ipywidgets>=8.1.5
Requires-Dist: lmfit
Requires-Dist: matplotlib<3.9.0
Requires-Dist: numpy<2.0
Requires-Dist: packaging
Requires-Dist: pandas
Requires-Dist: pyperclip
Requires-Dist: scipy
